README.md
setup.py
route1io_connectors/__init__.py
route1io_connectors/adthena.py
route1io_connectors/apple_search_ads.py
route1io_connectors/aws.py
route1io_connectors/facebook.py
route1io_connectors/linkedin.py
route1io_connectors/onedrive.py
route1io_connectors/quickbooks.py
route1io_connectors/slack.py
route1io_connectors/tiktok.py
route1io_connectors.egg-info/PKG-INFO
route1io_connectors.egg-info/SOURCES.txt
route1io_connectors.egg-info/dependency_links.txt
route1io_connectors.egg-info/requires.txt
route1io_connectors.egg-info/top_level.txt
route1io_connectors/automation/__init__.py
route1io_connectors/automation/extract.py
route1io_connectors/automation/load.py
route1io_connectors/automation/connectors/__init__.py
route1io_connectors/automation/connectors/gsheets.py
route1io_connectors/automation/connectors/s3.py
route1io_connectors/google/__init__.py
route1io_connectors/google/credentials.py
route1io_connectors/google/dcm.py
route1io_connectors/google/drive.py
route1io_connectors/google/google_ads.py
route1io_connectors/google/google_analytics.py
route1io_connectors/google/gsheets.py
route1io_connectors/google/sa360.py
route1io_connectors/google/utils/__init__.py
route1io_connectors/google/utils/_ga4.py
route1io_connectors/google/utils/_universal_analytics.py
route1io_connectors/utils/__init__.py
route1io_connectors/utils/date_range.py
route1io_connectors/utils/endpoints.py