Metadata-Version: 2.1
Name: route1io-connectors
Version: 0.20.0
Summary: Connectors for interacting with popular API's used in marketing analytics using clean and concise Python code.
Home-page: https://github.com/route1io/route1io-python-connectors
Author: route1.io
Author-email: developers@route1.io
License: GPLv3
Platform: UNKNOWN
Classifier: License :: OSI Approved :: GNU General Public License v3 (GPLv3)
Classifier: Programming Language :: Python :: 3
